figures/verilog/decimal_counter.v
`timescale 1us/1ns

// Decimal counter built from a 74HC161-like binary counter plus
// active-low asynchronous clear generated when Q = 1010.
module decimal_counter (
    input  wire clk,
    input  wire ext_clr_n,
    input  wire en,
    output reg  [3:0] q,
    output wire decode_10,
    output wire clr_n
);
    assign decode_10 = q[3] & ~q[2] & q[1] & ~q[0];

    // A small gate delay makes the asynchronous clear pulse visible in GTKWave.
    assign #2 clr_n = ext_clr_n & ~decode_10;

    always @(posedge clk or negedge clr_n) begin
        if (!clr_n) begin
            q <= 4'b0000;
        end else if (en) begin
            q <= q + 4'b0001;
        end
    end
endmodule

figures/verilog/tb_decimal_counter.v
`timescale 1us/1ns

module tb_decimal_counter;
    reg clk = 1'b0;
    reg ext_clr_n = 1'b1;
    reg en = 1'b1;
    wire [3:0] q;
    wire q0 = q[0];
    wire q1 = q[1];
    wire q2 = q[2];
    wire q3 = q[3];
    wire decode_10;
    wire clr_n;

    // 1 kHz square wave: period = 1 ms = 1000 us.
    always #500 clk = ~clk;

    decimal_counter dut (
        .clk(clk),
        .ext_clr_n(ext_clr_n),
        .en(en),
        .q(q),
        .decode_10(decode_10),
        .clr_n(clr_n)
    );

    initial begin
        $dumpfile("decimal_counter.vcd");
        $dumpvars(0, tb_decimal_counter);

        // Generate a real active-low asynchronous clear pulse before counting.
        #100 ext_clr_n = 1'b0;
        #100 ext_clr_n = 1'b1;

        // Run long enough to show two complete 0..9 cycles.
        #22000 $finish;
    end
endmodule

figures/verilog/decimal_counter.vcd
$date
	Sun Jun  7 15:16:20 2026
$end
$version
	Icarus Verilog
$end
$timescale
	1ns
$end
$scope module tb_decimal_counter $end
$var wire 1 ! q3 $end
$var wire 1 " q2 $end
$var wire 1 # q1 $end
$var wire 1 $ q0 $end
$var wire 4 % q [3:0] $end
$var wire 1 & decode_10 $end
$var wire 1 ' clr_n $end
$var reg 1 ( clk $end
$var reg 1 ) en $end
$var reg 1 * ext_clr_n $end
$scope module dut $end
$var wire 1 ( clk $end
$var wire 1 ' clr_n $end
$var wire 1 & decode_10 $end
$var wire 1 ) en $end
$var wire 1 * ext_clr_n $end
$var reg 4 + q [3:0] $end
$upscope $end
$upscope $end
$enddefinitions $end
$comment Show the parameter values. $end
$dumpall
$end
#0
$dumpvars
bx +
1*
1)
0(
x'
x&
bx %
x$
x#
x"
x!
$end
#100000
0*
#102000
0&
0!
0"
0#
0$
b0 %
b0 +
0'
#200000
1*
#202000
1'
#500000
1$
b1 %
b1 +
1(
#1000000
0(
#1500000
1#
0$
b10 %
b10 +
1(
#2000000
0(
#2500000
1$
b11 %
b11 +
1(
#3000000
0(
#3500000
1"
0#
0$
b100 %
b100 +
1(
#4000000
0(
#4500000
1$
b101 %
b101 +
1(
#5000000
0(
#5500000
1#
0$
b110 %
b110 +
1(
#6000000
0(
#6500000
1$
b111 %
b111 +
1(
#7000000
0(
#7500000
1!
0"
0#
0$
b1000 %
b1000 +
1(
#8000000
0(
#8500000
1$
b1001 %
b1001 +
1(
#9000000
0(
#9500000
1&
1#
0$
b1010 %
b1010 +
1(
#9502000
0&
0!
0#
b0 %
b0 +
0'
#9504000
1'
#10000000
0(
#10500000
1$
b1 %
b1 +
1(
#11000000
0(
#11500000
1#
0$
b10 %
b10 +
1(
#12000000
0(
#12500000
1$
b11 %
b11 +
1(
#13000000
0(
#13500000
1"
0#
0$
b100 %
b100 +
1(
#14000000
0(
#14500000
1$
b101 %
b101 +
1(
#15000000
0(
#15500000
1#
0$
b110 %
b110 +
1(
#16000000
0(
#16500000
1$
b111 %
b111 +
1(
#17000000
0(
#17500000
1!
0"
0#
0$
b1000 %
b1000 +
1(
#18000000
0(
#18500000
1$
b1001 %
b1001 +
1(
#19000000
0(
#19500000
1&
1#
0$
b1010 %
b1010 +
1(
#19502000
0&
0!
0#
b0 %
b0 +
0'
#19504000
1'
#20000000
0(
#20500000
1$
b1 %
b1 +
1(
#21000000
0(
#21500000
1#
0$
b10 %
b10 +
1(
